csst/analyzer/__init__.py
csst/analyzer/plotter.py
csst/db/__init__.py
csst/db/_base.py
csst/db/adder.py
csst/db/getter.py
csst/db/orm/__init__.py
csst/db/orm/csst.py
csst/db/orm/polymer.py
csst/db/orm/solvent.py
csst/experiment/__init__.py
csst/experiment/helpers.py
csst/experiment/models.py
csst/processor/__init__.py
csst/processor/helpers.py
csst/processor/models.py
csst_analyzer-4.0.1.dist-info/METADATA
csst_analyzer-4.0.1.dist-info/WHEEL
csst_analyzer-4.0.1.dist-info/RECORD
